Verilog/half_adder.v
`timescale 1ns/10ps
module half_adder (A,B,S,C);

input A,B;
output S,C;

xor inst1(S,A,B);
and inst2(C,A,B);

endmodule

Verilog/full_adder.v
`timescale 1ns/10ps
`include "./half_adder.v"
module full_adder (A,B,Cin,S,C);

input A,B,Cin;
output S,C;
wire S1,C1,X;

half_adder inst1(A,B,S1,C1);
half_adder inst2(Cin,S1,S,X);
or inst3(C,X,C1);

endmodule

Verilog/full_adder_tb.v
`timescale 1ns/10ps
module full_adder_tb;

reg A,B,Cin;
wire Sum,Carry;
integer i,k;

full_adder full_add(A,B,Cin,Sum,Carry);

initial
	begin
        $dumpfile("full_adder_tb.vcd");
        $dumpvars(0,full_adder_tb);
		
		A = 0;
		B = 0;
		Cin = 0;
	end

initial begin
	for (i = 1; i <= 8; i = i + 1)
		begin
			#10
			k = i;
			
			A = k % 2;
			k = k / 2;
			
			B = k % 2;
			k = k / 2;
			
			Cin = k % 2;
		end
end

always @(Sum,Carry)
	$display("time =%0t \t A =%b, B =%b, Cin =%b and Sum =%b, Carry =%b",$time,A,B,Cin,Sum,Carry);

endmodule

Verilog/full_adder_tb.vcd
$date
	Sun Nov 20 13:58:13 2022
$end
$version
	Icarus Verilog
$end
$timescale
	10ps
$end
$scope module full_adder_tb $end
$var wire 1 ! Sum $end
$var wire 1 " Carry $end
$var reg 1 # A $end
$var reg 1 $ B $end
$var reg 1 % Cin $end
$var integer 32 & i [31:0] $end
$var integer 32 ' k [31:0] $end
$scope module full_add $end
$var wire 1 # A $end
$var wire 1 $ B $end
$var wire 1 " C $end
$var wire 1 % Cin $end
$var wire 1 ( X $end
$var wire 1 ) S1 $end
$var wire 1 ! S $end
$var wire 1 * C1 $end
$scope module inst1 $end
$var wire 1 # A $end
$var wire 1 $ B $end
$var wire 1 * C $end
$var wire 1 ) S $end
$upscope $end
$scope module inst2 $end
$var wire 1 % A $end
$var wire 1 ) B $end
$var wire 1 ( C $end
$var wire 1 ! S $end
$upscope $end
$upscope $end
$upscope $end
$enddefinitions $end
$comment Show the parameter values. $end
$dumpall
$end
#0
$dumpvars
0*
0)
0(
bx '
b1 &
0%
0$
0#
0"
0!
$end
#1000
1!
1)
b10 &
1#
b0 '
#2000
b11 &
1$
0#
b0 '
#3000
0!
1"
0)
1*
b100 &
1#
b0 '
#4000
0"
1!
0*
b101 &
1%
0$
0#
b1 '
#5000
1"
0!
1(
1)
b110 &
1#
b1 '
#6000
b111 &
1$
0#
b1 '
#7000
1!
0(
0)
1*
b1000 &
1#
b1 '
#8000
0"
0!
0*
b1001 &
0%
0$
0#
b10 '
